{"_type":"export","__export_format":4,"__export_date":"2021-08-30T02:29:40.290Z","__export_source":"insomnia.desktop.app:v2021.5.0","resources":[{"_id":"req_2ff056e168fb425eb32cfba0f2a46fff","parentId":"wrk_78fb0a04b7944096b591ab9adcb92b83","modified":1630289783762,"created":1630289702636,"url":"http://localhost/api/user","name":"Register","description":"","method":"POST","body":{"mimeType":"application/json","text":"{\n\t\"name\": \"Bacon\",\n\t\"email\": \"bacon@email.com\",\n\t\"password\": \"senha123\"\n}"},"parameters":[],"headers":[{"name":"Content-Type","value":"application/json","id":"pair_3acf3f2da0b84253b5004fd2716a294e"}],"authentication":{},"metaSortKey":-1630289702636,"isPrivate":false,"settingStoreCookies":true,"settingSendCookies":true,"settingDisableRenderRequestBody":false,"settingEncodeUrl":true,"settingRebuildPath":true,"settingFollowRedirects":"global","_type":"request"},{"_id":"wrk_78fb0a04b7944096b591ab9adcb92b83","parentId":null,"modified":1624271892668,"created":1624271892668,"name":"Insomnia","description":"","scope":"collection","_type":"workspace"},{"_id":"req_44ffeb7f1caf431d9ceee5021d05027f","parentId":"wrk_78fb0a04b7944096b591ab9adcb92b83","modified":1630290453239,"created":1630289801900,"url":"http://localhost/api/login","name":"Login","description":"","method":"POST","body":{"mimeType":"application/json","text":"{\n\t\"email\": \"bacon@email.com\",\n\t\"password\": \"senha123\",\n\t\"token\": \"160119\"\n}"},"parameters":[],"headers":[{"name":"Content-Type","value":"application/json","id":"pair_3acf3f2da0b84253b5004fd2716a294e"}],"authentication":{},"metaSortKey":-1630289702586,"isPrivate":false,"settingStoreCookies":true,"settingSendCookies":true,"settingDisableRenderRequestBody":false,"settingEncodeUrl":true,"settingRebuildPath":true,"settingFollowRedirects":"global","_type":"request"},{"_id":"req_5cbc43da88774b57ad6655a92d547b7a","parentId":"wrk_78fb0a04b7944096b591ab9adcb92b83","modified":1630289832171,"created":1630289828229,"url":"http://localhost/api/login","name":"Check login","description":"","method":"GET","body":{"mimeType":"application/json","text":""},"parameters":[],"headers":[{"name":"Content-Type","value":"application/json","id":"pair_3acf3f2da0b84253b5004fd2716a294e"}],"authentication":{},"metaSortKey":-1630289702536,"isPrivate":false,"settingStoreCookies":true,"settingSendCookies":true,"settingDisableRenderRequestBody":false,"settingEncodeUrl":true,"settingRebuildPath":true,"settingFollowRedirects":"global","_type":"request"},{"_id":"req_e28ad14cc5354fa2bd87d90747bbb4f9","parentId":"wrk_78fb0a04b7944096b591ab9adcb92b83","modified":1630289876808,"created":1630289869216,"url":"http://localhost/api/login","name":"Logout","description":"","method":"DELETE","body":{},"parameters":[],"headers":[],"authentication":{},"metaSortKey":-1630289702486,"isPrivate":false,"settingStoreCookies":true,"settingSendCookies":true,"settingDisableRenderRequestBody":false,"settingEncodeUrl":true,"settingRebuildPath":true,"settingFollowRedirects":"global","_type":"request"},{"_id":"req_2c8fddbbd2624f0b88eda2de63a8e475","parentId":"wrk_78fb0a04b7944096b591ab9adcb92b83","modified":1630290261413,"created":1630290241965,"url":"http://localhost/api/login/otp","name":"Create OTP step","description":"","method":"POST","body":{},"parameters":[],"headers":[],"authentication":{},"metaSortKey":-1630289702436,"isPrivate":false,"settingStoreCookies":true,"settingSendCookies":true,"settingDisableRenderRequestBody":false,"settingEncodeUrl":true,"settingRebuildPath":true,"settingFollowRedirects":"global","_type":"request"},{"_id":"req_343f767aeff54fc6af2caefcbd537430","parentId":"wrk_78fb0a04b7944096b591ab9adcb92b83","modified":1630290490296,"created":1630290487708,"url":"http://localhost/api/login/otp","name":"Remove OTP step","description":"","method":"DELETE","body":{},"parameters":[],"headers":[],"authentication":{},"metaSortKey":-1630289702386,"isPrivate":false,"settingStoreCookies":true,"settingSendCookies":true,"settingDisableRenderRequestBody":false,"settingEncodeUrl":true,"settingRebuildPath":true,"settingFollowRedirects":"global","_type":"request"},{"_id":"env_624cd0d59869e1e9a8fa5d2fc3d839f61b705de3","parentId":"wrk_78fb0a04b7944096b591ab9adcb92b83","modified":1624271892721,"created":1624271892721,"name":"Base Environment","data":{},"dataPropertyOrder":null,"color":null,"isPrivate":false,"metaSortKey":1624271892721,"_type":"environment"},{"_id":"jar_624cd0d59869e1e9a8fa5d2fc3d839f61b705de3","parentId":"wrk_78fb0a04b7944096b591ab9adcb92b83","modified":1630290455539,"created":1624271892723,"name":"Default Jar","cookies":[{"key":"connect.sid","value":"s%3AtkHmcFOv7jiv5VDBpc4dsqrioX-EiCqq.LorNwPBxPavmxVSHQsMcTmKZPvssRfJ8rTcQ8ewfukA","domain":"localhost","path":"/","httpOnly":true,"hostOnly":true,"creation":"2021-08-30T02:16:26.053Z","lastAccessed":"2021-08-30T02:27:35.539Z","id":"14633439687123118"}],"_type":"cookie_jar"},{"_id":"spc_6c0ee72f1c254e4f911667a67e9d817b","parentId":"wrk_78fb0a04b7944096b591ab9adcb92b83","modified":1624271892669,"created":1624271892669,"fileName":"Insomnia","contents":"","contentType":"yaml","_type":"api_spec"}]}